Metadata-Version: 2.1
Name: friebox
Version: 1.0.3
Summary: friebox - Real-time collection tool for Android/iOS performance data.
Home-page: https://github.com/kamalyes/friebox
Author: Kamalyes
Author-email: mryu168@163.com
License: MIT
Classifier: Environment :: Console
Classifier: Intended Audience :: Developers
Classifier: Operating System :: OS Independent
Classifier: Programming Language :: Python :: 3
License-File: LICENSE
Requires-Dist: flask (>=2.1.3)
Requires-Dist: httpio (>=0.3.0)
Requires-Dist: requests (>=2.28.2)
Requires-Dist: logzero (>=1.7.0)
Requires-Dist: tidevice (>=0.10.7)
Requires-Dist: tqdm (>=4.65.0)
Requires-Dist: xlwt (>=1.3.0)
Requires-Dist: flask-socketio (>=5.3.3)
Requires-Dist: fire (>=0.5.0)
Requires-Dist: werkzeug (==2.0.3)
Requires-Dist: Jinja2 (==3.0.1)
